.gitignore
LICENSE.txt
README.backup.md
README.db.json
README.md
README.saved_paths.txt
README_ignore.py
setup.cfg
setup.py
yutils.code-workspace
.vscode/launch.json
yutils/__init__.py
yutils/_import.py
yutils.egg-info/PKG-INFO
yutils.egg-info/SOURCES.txt
yutils.egg-info/dependency_links.txt
yutils.egg-info/requires.txt
yutils.egg-info/top_level.txt
yutils/base/__init__.py
yutils/base/attribute_dict.py
yutils/base/generic_object.py
yutils/base/input_checker.py
yutils/base/list_container.py
yutils/base/pretty_printer.py
yutils/base/updating_dict.py
yutils/conn/__init__.py
yutils/conn/sql_connection_details.py
yutils/exceptions/__init__.py
yutils/exceptions/exceptions.py
yutils/ml/__init__.py
yutils/ml/base/__init__.py
yutils/ml/base/ml_base.py
yutils/ml/data/__init__.py
yutils/ml/data/data_sets.py
yutils/ml/data/features.py
yutils/ml/data/pca.py
yutils/ml/impl/__init__.py
yutils/ml/impl/gradient_checking.py
yutils/ml/impl/plotting/__init__.py
yutils/ml/impl/plotting/base.py
yutils/ml/impl/plotting/curves.py
yutils/ml/impl/plotting/j_cost.py
yutils/ml/impl/plotting/linear_hypothesis.py
yutils/ml/impl/plotting/plot_decision_boundary.py
yutils/ml/models/__init__.py
yutils/ml/models/supervised/__init__.py
yutils/ml/models/supervised/ml_optimizer.py
yutils/ml/models/supervised/supervised_model.py
yutils/ml/models/supervised/others/__init__.py
yutils/ml/models/supervised/others/continuous/__init__.py
yutils/ml/models/supervised/others/continuous/normal_equation.py
yutils/ml/models/supervised/regression/__init__.py
yutils/ml/models/supervised/regression/regression.py
yutils/ml/models/supervised/regression/classification/__init__.py
yutils/ml/models/supervised/regression/classification/classification.py
yutils/ml/models/supervised/regression/classification/logistic_regression.py
yutils/ml/models/supervised/regression/classification/multiclass_classification.py
yutils/ml/models/supervised/regression/classification/neural_network.py
yutils/ml/models/supervised/regression/classification/svm.py
yutils/ml/models/supervised/regression/continuous/__init__.py
