Metadata-Version: 2.1
Name: yutils
Version: 1.4.0
Summary: A Python utility package written by Yuval Arbel
Home-page: https://github.com/yuvalarbel
Author: Yuval Arbel
Author-email: yuval@arbels.net
License: MIT
Download-URL: https://github.com/yuvalarbel/yutils/archive/1.4.0.tar.gz
Keywords: utils,utilities,queries,ml,tools
Platform: UNKNOWN
Classifier: Development Status :: 4 - Beta
Classifier: Intended Audience :: Developers
Classifier: Topic :: Utilities
Classifier: License :: OSI Approved :: MIT License
Classifier: Programming Language :: Python :: 3.7
Classifier: Programming Language :: Python :: 3.8
